docplus.py
docplus-0.0.3.dist-info/LICENSE
docplus-0.0.3.dist-info/METADATA
docplus-0.0.3.dist-info/WHEEL
docplus-0.0.3.dist-info/top_level.txt
docplus-0.0.3.dist-info/RECORD
