Metadata-Version: 2.1
Name: docplus
Version: 0.0.3
Summary: Doc Utils APIs
Author-email: ChanMo <chan.mo@outlook.com>
Project-URL: Homepage, https://github.com/ChanMo/docker-doc-utils
Project-URL: Bug Tracker, https://github.com/ChanMo/docker-doc-utils/issues
Classifier: Programming Language :: Python :: 3
Classifier: License :: OSI Approved :: MIT License
Classifier: Operating System :: OS Independent
Requires-Python: >3.7
License-File: LICENSE
